AUTHORS
INSTALL
LICENSE
MANIFEST.in
NOTICE
README
requirements.txt
setup.cfg
setup.py
docs/Makefile
docs/conf.py
docs/configuration.rst
docs/faq.rst
docs/index.rst
docs/installation.rst
docs/introduction.rst
docs/make.bat
docs/usage.rst
src/sysscope/__init__.py
src/sysscope/admin.py
src/sysscope/forms.py
src/sysscope/models.py
src/sysscope/settings.py
src/sysscope/tests.py
src/sysscope/urls.py
src/sysscope/utils.py
src/sysscope/views.py
src/sysscope.egg-info/PKG-INFO
src/sysscope.egg-info/SOURCES.txt
src/sysscope.egg-info/dependency_links.txt
src/sysscope.egg-info/not-zip-safe
src/sysscope.egg-info/top_level.txt
src/sysscope/core/__init__.py
src/sysscope/core/commons.py
src/sysscope/core/config.py
src/sysscope/core/exceptions.py
src/sysscope/core/graphbase.py
src/sysscope/core/syntax.py
src/sysscope/static/sysscope/css/style.css
src/sysscope/templates/sysscope/archive_links.html
src/sysscope/templates/sysscope/base.html
src/sysscope/templates/sysscope/graph_archive.html
src/sysscope/templates/sysscope/nav_timeframe_browser.html
src/sysscope/templates/sysscope/nav_timeframe_selector.html
src/sysscope/templates/sysscope/section.html
src/sysscope/templates/sysscope/section_links.html
src/sysscope/templates/sysscope/start.html
src/sysscope/templatetags/__init__.py
src/sysscope/templatetags/sysscope_tags.py