Metadata-Version: 1.1
Name: sysscope
Version: 1.0.11a1
Summary: sysscope - Tool for visual representation of RRDtool's Round Robin Databases.
Home-page: http://www.codetrax.org/projects/sysscope
Author: George Notaras
Author-email: gnot [at] g-loaded.eu
License: Apache License version 2
Download-URL: https://source.codetrax.org/hgroot/sysscope
Platform: any
Classifier: Development Status :: 3 - Alpha
Classifier: Environment :: Web Environment
Classifier: Framework :: Django
Classifier: Intended Audience :: Developers
Classifier: License :: OSI Approved :: Apache Software License
Classifier: Natural Language :: English
Classifier: Operating System :: OS Independent
Classifier: Programming Language :: Python
Classifier: Topic :: Internet :: WWW/HTTP :: Dynamic Content
Classifier: Topic :: Software Development :: Libraries :: Application Frameworks
Classifier: Topic :: Software Development :: Libraries :: Python Modules
